setup.py
dsnd_probability_nikhat/Binomialdistribution.py
dsnd_probability_nikhat/Gaussiandistribution.py
dsnd_probability_nikhat/Generaldistribution.py
dsnd_probability_nikhat/__init__.py
dsnd_probability_nikhat.egg-info/PKG-INFO
dsnd_probability_nikhat.egg-info/SOURCES.txt
dsnd_probability_nikhat.egg-info/dependency_links.txt
dsnd_probability_nikhat.egg-info/not-zip-safe
dsnd_probability_nikhat.egg-info/top_level.txt